cg/__init__.py
cg/apps/__init__.py
cg/apps/coverage/__init__.py
cg/apps/coverage/api.py
cg/apps/crunchy/__init__.py
cg/apps/crunchy/crunchy.py
cg/apps/crunchy/files.py
cg/apps/crunchy/models.py
cg/apps/crunchy/sbatch.py
cg/apps/demultiplex/__init__.py
cg/apps/demultiplex/demultiplex_api.py
cg/apps/demultiplex/sample_sheet/__init__.py
cg/apps/demultiplex/sample_sheet/api.py
cg/apps/demultiplex/sample_sheet/index.py
cg/apps/demultiplex/sample_sheet/override_cycles_validator.py
cg/apps/demultiplex/sample_sheet/read_sample_sheet.py
cg/apps/demultiplex/sample_sheet/sample_models.py
cg/apps/demultiplex/sample_sheet/sample_sheet_creator.py
cg/apps/demultiplex/sample_sheet/sample_sheet_models.py
cg/apps/demultiplex/sample_sheet/sample_sheet_validator.py
cg/apps/demultiplex/sample_sheet/utils.py
cg/apps/demultiplex/sample_sheet/validators.py
cg/apps/demultiplex/sbatch.py
cg/apps/downsample/__init__.py
cg/apps/downsample/downsample.py
cg/apps/downsample/utils.py
cg/apps/environ.py
cg/apps/gens.py
cg/apps/gt.py
cg/apps/hermes/__init__.py
cg/apps/hermes/hermes_api.py
cg/apps/hermes/models.py
cg/apps/housekeeper/__init__.py
cg/apps/housekeeper/hk.py
cg/apps/housekeeper/models.py
cg/apps/invoice/__init__.py
cg/apps/invoice/render.py
cg/apps/invoice/templates/KI_pool_invoice.xlsx
cg/apps/invoice/templates/KI_sample_invoice.xlsx
cg/apps/invoice/templates/KTH_pool_invoice.xlsx
cg/apps/invoice/templates/KTH_sample_invoice.xlsx
cg/apps/lims/__init__.py
cg/apps/lims/api.py
cg/apps/lims/batch.py
cg/apps/lims/order.py
cg/apps/lims/sample_sheet.py
cg/apps/loqus.py
cg/apps/madeline/__init__.py
cg/apps/madeline/api.py
cg/apps/mip/__init__.py
cg/apps/mip/confighandler.py
cg/apps/mutacc_auto.py
cg/apps/orderform/__init__.py
cg/apps/orderform/excel_orderform_parser.py
cg/apps/orderform/json_orderform_parser.py
cg/apps/orderform/orderform_parser.py
cg/apps/orderform/utils.py
cg/apps/scout/__init__.py
cg/apps/scout/scout_export.py
cg/apps/scout/scoutapi.py
cg/apps/scout/validators.py
cg-83.18.2.dist-info/METADATA
cg-83.18.2.dist-info/WHEEL
cg-83.18.2.dist-info/entry_points.txt
cg-83.18.2.dist-info/RECORD
