Metadata-Version: 2.4
Name: cg
Version: 83.18.2
Summary: Clinical Genomics command center
Requires-Python: >=3.11,<3.13
Classifier: Programming Language :: Python
Classifier: Programming Language :: Python :: 3.11
Classifier: Programming Language :: Python :: Implementation :: CPython
Provides-Extra: coveralls
Provides-Extra: mock
Provides-Extra: pre-commit
Provides-Extra: pytest
Provides-Extra: pytest-cov
Provides-Extra: pytest-freezegun
Provides-Extra: pytest-httpserver
Provides-Extra: pytest-mock
Provides-Extra: pytest-xdist
Provides-Extra: ruff
Requires-Dist: CacheControl
Requires-Dist: Flask
Requires-Dist: Flask-Admin
Requires-Dist: Flask-CORS
Requires-Dist: Flask-Dance
Requires-Dist: Flask-WTF
Requires-Dist: Jinja2
Requires-Dist: MarkupSafe
Requires-Dist: PyMySQL
Requires-Dist: PyYAML
Requires-Dist: SQLAlchemy
Requires-Dist: WTForms (==3.0.0)
Requires-Dist: alembic
Requires-Dist: blinker
Requires-Dist: cachetools
Requires-Dist: click
Requires-Dist: coloredlogs
Requires-Dist: coveralls ; extra == "coveralls"
Requires-Dist: cryptography
Requires-Dist: email-validator (>=2.2.0)
Requires-Dist: genologics
Requires-Dist: google-auth
Requires-Dist: gunicorn
Requires-Dist: housekeeper (==4.13.15)
Requires-Dist: lxml
Requires-Dist: marshmallow
Requires-Dist: mock ; extra == "mock"
Requires-Dist: openpyxl
Requires-Dist: packaging
Requires-Dist: pandas
Requires-Dist: paramiko
Requires-Dist: petname
Requires-Dist: pre-commit ; extra == "pre-commit"
Requires-Dist: psutil
Requires-Dist: pydantic (==2.7.4)
Requires-Dist: pydantic-settings (>=2.3.3)
Requires-Dist: pytest ; extra == "pytest"
Requires-Dist: pytest-cov ; extra == "pytest-cov"
Requires-Dist: pytest-freezegun ; extra == "pytest-freezegun"
Requires-Dist: pytest-httpserver ; extra == "pytest-httpserver"
Requires-Dist: pytest-mock ; extra == "pytest-mock"
Requires-Dist: pytest-xdist ; extra == "pytest-xdist"
Requires-Dist: python-dateutil
Requires-Dist: requests
Requires-Dist: rich-click (>=1.8.4)
Requires-Dist: ruff ; extra == "ruff"
Requires-Dist: tabulate
Requires-Dist: typing_extensions
Requires-Dist: urllib3
Requires-Dist: werkzeug
